<?xml version="1.0" encoding="UTF-8"?>
<Countries>
  <Country name="Ukraine">
    <Regions>
      <Region name="Ukraine">
        <stadium name="Arsenal Stadium" capacity="5900"/>
        <stadium name="Chornomorets Stadium" capacity="11000"/>
        <stadium name="Dinamo Kiev Stadium" capacity="32200"/>
        <stadium name="Dnipro Stadium" capacity="14200"/>
        <stadium name="Karpaty Stadium" capacity="3300"/>
        <stadium name="Kharkiv Stadium" capacity="2700"/>
        <stadium name="Kryvbas Stadium" capacity="2700"/>
        <stadium name="Metalist Stadium" capacity="11600"/>
        <stadium name="Metalurg D Stadium" capacity="10900"/>
        <stadium name="Metalurg Z Stadium" capacity="2500"/>
        <stadium name="Naftovyk Stadium" capacity="2000"/>
        <stadium name="Shakhtar Donetsk Stadium" capacity="44600"/>
        <stadium name="Tavriya Stadium" capacity="2800"/>
        <stadium name="Vorskla Stadium" capacity="2900"/>
        <stadium name="Stal Stadium" capacity="1300"/>
        <stadium name="Illychivets Stadium" capacity="1200"/>
        <stadium name="Zakarpattya Stadium" capacity="1500"/>
        <stadium name="Zorya Stadium" capacity="2700"/>
      </Region>
    </Regions>
    <leaguesystem name="Ukrainian league">
      <Levels>
        <level>
          <branch>
            <stage name="Premier league" type="0">
              <setup seeded="0" participantnum="18" groups="1" rounds="2" pointsperwin="3"/>
              <trophy name="Ukrainian Premier league champion"/>
              <attendances>
                <attendance tournament="Ukrainian Cup" stage="First round"/>
              </attendances>
              <preset>
                <club name="Arsenal"/>
                <club name="Chornomorets"/>
                <club name="Dinamo Kiev"/>
                <club name="Dnipro"/>
                <club name="Karpaty"/>
                <club name="Kharkiv"/>
                <club name="Kryvbas"/>
                <club name="Metalist"/>
                <club name="Metalurg D"/>
                <club name="Metalurg Z"/>
                <club name="Naftovyk"/>
                <club name="Shakhtar Donetsk"/>
                <club name="Tavriya"/>
                <club name="Vorskla"/>
                <club name="Stal"/>
                <club name="Illychivets"/>
                <club name="Zakarpattya"/>
                <club name="Zorya"/>
              </preset>
            </stage>
          </branch>
          <leagueprs/>
          <leaguerls/>
        </level>
      </Levels>
    </leaguesystem>
    <Tournaments>
      <tournament name="Ukrainian Cup">
        <stage name="Final" type="1">
          <setup seeded="0" participantnum="2" rounds="1" extratime="1" replays="0" awaygoals="0"/>
          <trophy name="Ukrainian Cup champion"/>
        </stage>
        <stage name="Semifinals" type="1">
          <setup seeded="0" participantnum="4" rounds="1" extratime="1" replays="0" awaygoals="0"/>
          <cuppr stage="Final"/>
        </stage>
        <stage name="Quarterfinals" type="1">
          <setup seeded="0" participantnum="8" rounds="1" extratime="1" replays="0" awaygoals="0"/>
          <cuppr stage="Semifinals"/>
        </stage>
        <stage name="First round" type="1">
          <setup seeded="0" participantnum="16" rounds="1" extratime="1" replays="0" awaygoals="0"/>
          <cuppr stage="Quarterfinals"/>
          <preset>
            <club name="Arsenal"/>
            <club name="Chornomorets"/>
            <club name="Dinamo Kiev"/>
            <club name="Dnipro"/>
            <club name="Karpaty"/>
            <club name="Kharkiv"/>
            <club name="Kryvbas"/>
            <club name="Metalist"/>
            <club name="Metalurg D"/>
            <club name="Metalurg Z"/>
            <club name="Naftovyk"/>
            <club name="Shakhtar Donetsk"/>
            <club name="Tavriya"/>
            <club name="Vorskla"/>
            <club name="Stal"/>
            <club name="Illychivets"/>
          </preset>
        </stage>
      </tournament>
    </Tournaments>
  </Country>
</Countries>
